ihs29x/TwoNinetyEight.json
ihs29x/TwoNinetySeven.json
ihs29x/__init__.py
ihs29x/py.typed
ihs29x-0.1.0.dist-info/LICENSE
ihs29x-0.1.0.dist-info/WHEEL
ihs29x-0.1.0.dist-info/METADATA
ihs29x-0.1.0.dist-info/RECORD
