Metadata-Version: 2.1
Name: ihs29x
Version: 0.1.0
Summary: Spec-driven minimalist parser for IHS 297 and 298 formats
Author-email: "Derrick W. Turk" <dwt@terminusdatascience.com>
Requires-Python: >=3.10
Classifier: Programming Language :: Python :: Implementation :: CPython
Requires-Dist: importlib-resources
Requires-Dist: build ; extra == "dev"
Requires-Dist: mypy ; extra == "dev"
Requires-Dist: twine ; extra == "dev"
Requires-Dist: vulture ; extra == "dev"
Requires-Dist: pdoc ; extra == "docs"
Project-URL: Documentation, https://derrickturk.github.io/ihs29x-python/docs/ihs29x.html
Project-URL: Homepage, https://github.com/derrickturk/ihs29x-python
Project-URL: Repository, https://github.com/derrickturk/ihs29x-python
Provides-Extra: dev
Provides-Extra: docs
